stactools/glad_global_forest_change/__init__.py
stactools/glad_global_forest_change/cogs.py
stactools/glad_global_forest_change/commands.py
stactools/glad_global_forest_change/constants.py
stactools/glad_global_forest_change/stac.py
stactools_glad_global_forest_change-0.1.2.dist-info/licenses/LICENSE
stactools_glad_global_forest_change-0.1.2.dist-info/METADATA
stactools_glad_global_forest_change-0.1.2.dist-info/WHEEL
stactools_glad_global_forest_change-0.1.2.dist-info/top_level.txt
stactools_glad_global_forest_change-0.1.2.dist-info/RECORD
