Metadata-Version: 2.4
Name: stactools-glad-global-forest-change
Version: 0.1.2
Summary: stactools package for the GLAD Global Forest Change dataset
Author-email: Henry Rodman <henry@developmentseed.org>
Maintainer-email: Henry Rodman <henry@developmentseed.org>
License: Apache-2.0
Project-URL: Github, https://github.com/stactools-packages/glad-global-forest-change
Project-URL: Issues, https://github.com/stactools-packages/glad-global-forest-change/issues
Keywords: stactools,pystac,catalog,STAC
Classifier: Development Status :: 3 - Alpha
Classifier: Intended Audience :: Developers
Classifier: License :: OSI Approved :: Apache Software License
Classifier: Natural Language :: English
Classifier: Programming Language :: Python :: 3
Classifier: Programming Language :: Python :: 3.10
Classifier: Programming Language :: Python :: 3.11
Classifier: Programming Language :: Python :: 3.12
Classifier: Programming Language :: Python :: 3.13
Requires-Python: >=3.10
License-File: LICENSE
Requires-Dist: rasterio
Requires-Dist: parse>=1.20.2
Requires-Dist: pystac<2.0.0,>=1.11.0
Requires-Dist: rio-stac>=0.10.0
Requires-Dist: stactools>=0.5.0
Requires-Dist: semver>=3.0.4
Provides-Extra: cogs
Requires-Dist: boto3>=1.37.1; extra == "cogs"
Requires-Dist: httpx>=0.28.1; extra == "cogs"
Requires-Dist: obstore>=0.4.0; extra == "cogs"
Requires-Dist: rio-cogeo>=5.4.1; extra == "cogs"
Requires-Dist: tqdm>=4.67.1; extra == "cogs"
Dynamic: license-file
